xaal/__init__.py
xaal/edisio/__init__.py
xaal/edisio/__main__.py
xaal/edisio/gw.py
xaal_edisio-0.2.2.dist-info/METADATA
xaal_edisio-0.2.2.dist-info/WHEEL
xaal_edisio-0.2.2.dist-info/top_level.txt
xaal_edisio-0.2.2.dist-info/RECORD
